LICENSE
README.md
setup.py
pyqe/__init__.py
pyqe/pyqe.py
quantum_expresso_analize.egg-info/PKG-INFO
quantum_expresso_analize.egg-info/SOURCES.txt
quantum_expresso_analize.egg-info/dependency_links.txt
quantum_expresso_analize.egg-info/requires.txt
quantum_expresso_analize.egg-info/top_level.txt