Metadata-Version: 2.1
Name: quantum-expresso-analize
Version: 1.0.0
Summary: Quantum expresso data analize
Home-page: UNKNOWN
Author: Rafael Barreto
Author-email: rafinhareis17@gmail.com
License: MIT License
Keywords: quantum expresso
Platform: UNKNOWN
License-File: LICENSE
